docs/source/conf.py
heightmap_interpolation/__init__.py
heightmap_interpolation/apps/__init__.py
heightmap_interpolation/apps/apps_common.py
heightmap_interpolation/apps/erase_areas.py
heightmap_interpolation/apps/interpolate_netcdf4.py
heightmap_interpolation/apps/interpolate_xyz.py
heightmap_interpolation/apps/netcdf_data_io.py
heightmap_interpolation/apps/print_netcdf.py
heightmap_interpolation/apps/randomly_sample_xyz_from_netcdf4.py
heightmap_interpolation/apps/deprecated/common.py
heightmap_interpolation/apps/deprecated/inpaint_netcdf4.py
heightmap_interpolation/apps/deprecated/rbf_interpolate_netcdf4.py
heightmap_interpolation/inpainting/__init__.py
heightmap_interpolation/inpainting/amle_inpainter.py
heightmap_interpolation/inpainting/ccst_inpainter.py
heightmap_interpolation/inpainting/convolve_at_mask.py
heightmap_interpolation/inpainting/convolver.py
heightmap_interpolation/inpainting/differential.py
heightmap_interpolation/inpainting/exemplar_based_inpainter.py
heightmap_interpolation/inpainting/fd_pde_inpainter.py
heightmap_interpolation/inpainting/fd_pde_inpainter_factory.py
heightmap_interpolation/inpainting/initializer.py
heightmap_interpolation/inpainting/opencv_inpainter.py
heightmap_interpolation/inpainting/sobolev_inpainter.py
heightmap_interpolation/inpainting/taichi_fd_pde_inpainter.py
heightmap_interpolation/inpainting/tv_inpainter.py
heightmap_interpolation/inpainting/update_at_mask.py
heightmap_interpolation/interpolants/__init__.py
heightmap_interpolation/interpolants/cubic_interpolant.py
heightmap_interpolation/interpolants/distance_type_to_functor.py
heightmap_interpolation/interpolants/interpolant.py
heightmap_interpolation/interpolants/linear_interpolant.py
heightmap_interpolation/interpolants/nearest_neighbor_interpolant.py
heightmap_interpolation/interpolants/quad_tree_pu_rbf_interpolant.py
heightmap_interpolation/interpolants/rbf_interpolant.py
heightmap_interpolation/misc/__init__.py
heightmap_interpolation-1.0.6.dist-info/LICENSE
heightmap_interpolation-1.0.6.dist-info/METADATA
heightmap_interpolation-1.0.6.dist-info/WHEEL
heightmap_interpolation-1.0.6.dist-info/entry_points.txt
heightmap_interpolation-1.0.6.dist-info/top_level.txt
heightmap_interpolation-1.0.6.dist-info/RECORD
