Metadata-Version: 2.1
Name: heightmap_interpolation
Version: 1.0.6
Summary: Interpolation functions for heightmaps developed within the EMODnet Bathymetry (High Resolution Seabed Mapping) project.
Author-email: Ricard Campos <ricard.campos@coronis.es>
License:                    GNU LESSER GENERAL PUBLIC LICENSE
Classifier: Programming Language :: Python :: 3.10
Classifier: Operating System :: OS Independent
Classifier: Natural Language :: English
Requires-Python: >=3.10
License-File: LICENSE
Requires-Dist: packaging>=21.0
Requires-Dist: matplotlib>=3.5.0b1
Requires-Dist: numpy>=1.20.3
Requires-Dist: haversine>=2.5.1
Requires-Dist: scipy>=1.7.1
Requires-Dist: netCDF4>=1.5.7
Requires-Dist: geopy>=2.2.0
Requires-Dist: pandas>=1.3.2
Requires-Dist: geopandas>=0.9.0
Requires-Dist: opencv-python>=4.5.3.56
Requires-Dist: opencv-contrib-python>=4.5.3.56
Requires-Dist: numba>=0.54.1
Requires-Dist: psutil>=5.8.0
Requires-Dist: pyproj>=3.2.0
Requires-Dist: taichi
Requires-Dist: sphinx
Requires-Dist: sphinx-rtd-theme
Requires-Dist: exemplar-based-inpainting
